{
  "ar": {
    "validation_errors": {
      "repair_report_number": "يرجى إدخال رقم صحيح أكبر من صفر",
      "reporting_date": "يرجى إدخال تاريخ صحيح",
      "location": "يرجى إدخال موقع صحيح",
      "office": "يرجى إدخال مكتب صحيح",
      "number_of_office": "يرجى إدخال عدد صحيح أكبر من صفر",
      "number_of_floor": "يرجى إدخال عدد صحيح أكبر من صفر",
      "number_of_flat": "يرجى إدخال عدد صحيح أكبر من صفر",
      "type_of_fault": "يرجى إختيار نوع عطل صحيح"
    },
    "min_number_is_one": "الحد الأدنى للرقم هو واحد",
    "the_field_is_required": "هذا الحقل مطلوب",
    "add_attachments": "إضافة مرفقات",
    "date": "التاريخ",
    "employee_name": " اسم الموظف",
    "admin_name": "اسم المسؤول",
    "next": "التالي",
    "previous": "السابق",
    "suitable_date_to_attend": "التاريخ المناسب لحضور الفني",
    "analytics": "التحليلات",
    "hour": "الساعة",
    "fault_location": "مكان العطل",
    "enter_fault_location": "أدخل مكان العطل",
    "fault_description": "وصف العطل",
    "notes": "ملاحظات",
    "write_your_note_here": "اكتب ملاحظتك هنا",
    "overview": "نظرة عامة",
    "dashboard": "لوحة التحكم",
    "users": "المستخدمين",
    "roles": "الأدوار",
    "permissions": "الصلاحيات",
    "settings": "الإعدادات",
    "logout": "تسجيل الخروج",
    "profile": "الملف الشخصي",
    "name": "الاسم",
    "email": "البريد الإلكتروني",
    "password": "كلمة المرور",
    "confirm_password": "تأكيد كلمة المرور",
    "save": "حفظ",
    "cancel": "إلغاء",
    "add": "إضافة",
    "edit": "تعديل",
    "delete": "حذف",
    "show": "عرض",
    "actions": "العمليات",
    "no_data": "لا يوجد بيانات",
    "are_you_sure": "هل أنت متأكد؟",
    "yes": "نعم",
    "no": "لا",
    "close": "إغلاق",
    "search": "بحث",
    "id": "الرقم",
    "created_at": "تاريخ الإنشاء",
    "updated_at": "تاريخ التعديل",
    "permissions_list": "قائمة الصلاحيات",
    "permissions_create": "إضافة صلاحية",
    "permissions_edit": "تعديل صلاحية",
    "permissions_show": "عرض صلاحية",
    "permissions_delete": "حذف صلاحية",
    "roles_list": "قائمة الأدوار",
    "roles_create": "إضافة دور",
    "roles_edit": "تعديل دور",
    "roles_show": "عرض دور",
    "roles_delete": "حذف دور",
    "users_list": "قائمة المستخدمين",
    "users_create": "إضافة مستخدم",
    "users_edit": "تعديل مستخدم",
    "users_show": "عرض مستخدم",
    "users_delete": "حذف مستخدم",
    "settings_list": "قائمة الإعدادات",
    "settings_create": "إضافة إعداد",
    "settings_edit": "تعديل إعداد",
    "settings_show": "عرض إعداد",
    "settings_delete": "حذف إعداد",
    "settings_key": "المفتاح",
    "settings_value": "القيمة",
    "settings_type": "النوع",
    "settings_type_text": "نص",
    "settings_type_textarea": "نص طويل",
    "settings_type_number": "رقم",
    "settings_type_email": "بريد إلكتروني",
    "settings_type_password": "كلمة مرور",
    "settings_type_select": "قائمة منسدلة",
    "settings_type_checkbox": "خانة اختيار",
    "settings_type_radio": "زر اختيار",
    "settings_type_file": "ملف",
    "settings_type_image": "صورة",
    "settings_type_color": "لون",
    "settings_type_date": "تاريخ",
    "settings_type_time": "وقت",
    "settings_type_datetime": "تاريخ ووقت",
    "settings_type_url": "رابط",
    "settings_type_tel": "هاتف",
    "settings_type_range": "مدى",
    "settings_type_search": "بحث",
    "settings_type_month": "شهر",
    "settings_type_week": "أسبوع",
    "settings_type_hidden": "مخفي",
    "settings_type_reset": "إعادة تعيين",
    "settings_type_submit": "إرسال",
    "settings_type_button": "زر",
    "settings_type_text_help": "نص توضيحي",
    "settings_type_textarea_help": "نص طويل توضيحي",
    "settings_type_number_help": "رقم توضيحي",
    "settings_type_email_help": "بريد إلكتروني توضيحي",
    "settings_type_password_help": "كلمة مرور توضيحي",
    "office": "المكتب",
    "location": "المكان",
    "number_of_office": "رقم المكتب",
    "number_of_flat": "رقم الشقة",
    "number_of_floor": "رقم الطابق",
    "number_of_building": "رقم المبنى",
    "number_of_street": "رقم الشارع",
    "technical_support": "الدعم الفني",
    "technical_support_email": "البريد الإلكتروني للدعم الفني",
    "technical_support_phone": "رقم الهاتف للدعم الفني",
    "technical_support_address": "عنوان الدعم الفني",
    "technical_support_facebook": "فيسبوك الدعم الفني",
    "technical_support_twitter": "تويتر الدعم الفني",
    "technical_support_instagram": "إنستجرام الدعم الفني",
    "technical_support_youtube": "يوتيوب الدعم الفني",
    "technical_support_linkedin": "لينكد إن الدعم الفني",
    "technical_reports_list": "قائمة التقارير الفنية",
    "technical_reports_and_repairs": "التقارير الفنية والإصلاح",
    "repair_requests": "طلبات الإصلاح",
    "repair_requests_list": "قائمة طلبات الإصلاح",
    "repair_requests_create": "إضافة طلب إصلاح",
    "technical_reports": "التقارير الفنية",
    "technical_reports_create": "إضافة تقرير فني",
    "technical_report": "تقرير فني",
    "technical_report_title": "عنوان التقرير",
    "technical_report_view": "عرض التقرير",
    "technical_report_download": "تحميل التقرير",
    "technical_report_delete": "حذف التقرير",
    "technical_report_created_at": "تاريخ إنشاء التقرير",
    "technical_report_updated_at": "تاريخ تعديل التقرير",
    "technical_report_deleted_at": "تاريخ حذف التقرير",
    "technical_report_deleted_at_help": "إذا تم حذف التقرير فلن يظهر للمستخدمين",
    "technical_report_edit": "تعديل التقرير",
    "repair_reports": "تقارير الإصلاح",
    "reporting_date": "تاريخ الإبلاغ",
    "repair_report_number": "رقم تقرير الإصلاح",
    "repair": "إصلاح",
    "repair_reports_list": "قائمة تقارير الإصلاح",
    "repair_reports_create": "إضافة تقرير إصلاح",
    "request_data": "بيانات الطلب",
    "repair_request": "طلب إصلاح",
    "repair_report": "تقرير إصلاح",
    "repair_report_title": "عنوان تقرير الإصلاح",
    "repair_report_view": "عرض تقرير الإصلاح",
    "repair_report_download": "تحميل تقرير الإصلاح",
    "repair_report_delete": "حذف تقرير الإصلاح",
    "repair_report_created_at": "تاريخ إنشاء تقرير الإصلاح",
    "repair_report_updated_at": "تاريخ تعديل تقرير الإصلاح",
    "repair_report_deleted_at": "تاريخ حذف تقرير الإصلاح",
    "repair_report_deleted_at_help": "إذا تم حذف تقرير الإصلاح فلن يظهر للمستخدمين",
    "repair_report_edit": "تعديل تقرير الإصلاح",
    "repair_report_status": "حالة تقرير الإصلاح",
    "repair_report_status_pending": "قيد الانتظار",
    "repair_report_status_in_progress": "قيد التنفيذ",
    "repair_report_status_done": "تم التنفيذ",
    "repair_report_status_canceled": "تم الإلغاء",
    "repair_report_status_help": "حالة تقرير الإصلاح",
    "maintenance_and_cleaning": "الصيانة والتنظيف",
    "maintenance": "صيانة",
    "cleaning": "تنظيف",
    "daily": "يومي",
    "weekly": "أسبوعي",
    "monthly": "شهري",
    "yearly": "سنوي",
    "quarterly": "ربع سنوي",
    "add_new_tab": "إضافة تبويب جديد",
    "add_new_option": "إضافة خيار جديد",
    "not_repairing_causion": "سبب عدم الإصلاح",
    "fixed": "تم الإصلاح",
    "not_fixed": "لم يتم الإصلاح",
    "not_repairing_causion_help": "سبب عدم الإصلاح",
    "describe_the_fault": "اوصف العطل بالتفصيل",
    "asset_name": "اسم القطعة",
    "technical_name": "اسم الفني",
    "supervisor_name": "اسم المشرف",
    "write_the_causion": "اكتب السبب"
  }
}
